kaircs/__init__.py
kaircs/release.py
kaircs/vsbs.py
kaircs/service/__init__.py
kaircs/service/fs.py
kaircs/service/http.py
kaircs-0.4.0.dist-info/DESCRIPTION.rst
kaircs-0.4.0.dist-info/METADATA
kaircs-0.4.0.dist-info/RECORD
kaircs-0.4.0.dist-info/WHEEL
kaircs-0.4.0.dist-info/metadata.json
kaircs-0.4.0.dist-info/top_level.txt
riak/__init__.py
riak/benchmark.py
riak/bucket.py
riak/content.py
riak/mapreduce.py
riak/multidict.py
riak/node.py
riak/resolver.py
riak/riak_error.py
riak/riak_object.py
riak/security.py
riak/table.py
riak/test_server.py
riak/ts_object.py
riak/tz.py
riak/util.py
riak/client/__init__.py
riak/client/index_page.py
riak/client/multi.py
riak/client/operations.py
riak/client/transport.py
riak/codecs/__init__.py
riak/codecs/http.py
riak/codecs/pbuf.py
riak/codecs/ttb.py
riak/codecs/util.py
riak/datatypes/__init__.py
riak/datatypes/counter.py
riak/datatypes/datatype.py
riak/datatypes/errors.py
riak/datatypes/flag.py
riak/datatypes/hll.py
riak/datatypes/map.py
riak/datatypes/register.py
riak/datatypes/set.py
riak/datatypes/types.py
riak/pb/__init__.py
riak/pb/messages.py
riak/pb/riak_dt_pb2.py
riak/pb/riak_kv_pb2.py
riak/pb/riak_pb2.py
riak/pb/riak_search_pb2.py
riak/pb/riak_ts_pb2.py
riak/pb/riak_yokozuna_pb2.py
riak/transports/__init__.py
riak/transports/feature_detect.py
riak/transports/pool.py
riak/transports/security.py
riak/transports/transport.py
riak/transports/http/__init__.py
riak/transports/http/connection.py
riak/transports/http/resources.py
riak/transports/http/search.py
riak/transports/http/stream.py
riak/transports/http/transport.py
riak/transports/tcp/__init__.py
riak/transports/tcp/connection.py
riak/transports/tcp/stream.py
riak/transports/tcp/transport.py
