Metadata-Version: 2.0
Name: kaircs
Version: 0.4.0
Summary: A small File Cloud Storage over Riak KV
Home-page: http://www.merchise.org/
Author: Merchise Autrement [~º/~]
Author-email: UNKNOWN
License: UNKNOWN
Platform: UNKNOWN
Classifier: Programming Language :: Python
Requires-Dist: six (>=1.8.0)
Requires-Dist: basho-erlastic (>=2.1.1)
Requires-Dist: flask (>=0.12.2)
Requires-Dist: protobuf (<2.7.0,>=2.4.1)
Requires-Dist: xoutil (<2.0,>=1.9.3); python_version < "3.6"
Requires-Dist: xoutil (>=1.9.3); python_version >= "3.6"
